xotl.ql-0.7.0-py2.7-nspkg.pth
xotl/ql/__init__.py
xotl/ql/core.py
xotl/ql/interfaces.py
xotl/ql/release.py
xotl/ql/scratch.py
xotl/ql/tools.py
xotl/ql/revenge/__init__.py
xotl/ql/revenge/customs.py
xotl/ql/revenge/eight.py
xotl/ql/revenge/exceptions.py
xotl/ql/revenge/parsers.py
xotl/ql/revenge/qst.py
xotl/ql/revenge/scanners.py
xotl/ql/revenge/spark.py
xotl/ql/revenge/tools.py
xotl/ql/revenge/walkers.py
xotl/ql/translation/__init__.py
xotl/ql/translation/monads.py
xotl/ql/translation/py.py
xotl.ql-0.7.0.dist-info/DESCRIPTION.rst
xotl.ql-0.7.0.dist-info/METADATA
xotl.ql-0.7.0.dist-info/RECORD
xotl.ql-0.7.0.dist-info/WHEEL
xotl.ql-0.7.0.dist-info/metadata.json
xotl.ql-0.7.0.dist-info/namespace_packages.txt
xotl.ql-0.7.0.dist-info/top_level.txt
