Metadata-Version: 2.0
Name: xotl.ql
Version: 0.7.0
Summary: A pythonic query language, with similar goals as LINQ had for C#
Home-page: http://github.com/merchise-autrement/
Author: Merchise Autrement
Author-email: info@merchise.org
License: GNU General Public License version 3 or later (GPLv3+)
Keywords: query language,python,xotl
Platform: UNKNOWN
Classifier: Development Status :: 5 - Production/Stable
Classifier: Programming Language :: Python
Classifier: Intended Audience :: Developers
Classifier: Intended Audience :: Science/Research
Classifier: Topic :: Database
Requires-Python: >=3.5,<3.8
Requires-Dist: xoutil (>=1.9.4)
Provides-Extra: doc
Requires-Dist: docutils (>=0.7); extra == 'doc'
Requires-Dist: Sphinx (>=1.0.7); extra == 'doc'
